rst2txt/__init__.py
rst2txt/__main__.py
rst2txt/writer.py
rst2txt-1.1.0.dist-info/LICENSE
rst2txt-1.1.0.dist-info/METADATA
rst2txt-1.1.0.dist-info/WHEEL
rst2txt-1.1.0.dist-info/entry_points.txt
rst2txt-1.1.0.dist-info/top_level.txt
rst2txt-1.1.0.dist-info/RECORD
